ev/__init__.py
ev/cli.py
ev/evaluator.py
ev/improvement.py
ev/versioning.py
ev/agent/__init__.py
ev/agent/composer.py
ev/agent/runner.py
ev/agent/config/__init__.py
ev/agent/config/eval/__init__.py
ev/agent/config/eval/system_prompt.j2
ev/agent/schema/__init__.py
ev/agent/schema/schema_enforcer.j2
ev/core/__init__.py
ev/core/config.py
ev/schema/__init__.py
ev/schema/eval_schema.py
ev/utils/__init__.py
ev/utils/logger.py
ev/utils/model_util.py
ev/utils/pretty.py
evx-0.1.3.3.dist-info/licenses/LICENSE
evx-0.1.3.3.dist-info/METADATA
evx-0.1.3.3.dist-info/WHEEL
evx-0.1.3.3.dist-info/entry_points.txt
evx-0.1.3.3.dist-info/top_level.txt
evx-0.1.3.3.dist-info/RECORD
