Metadata-Version: 2.4
Name: evx
Version: 0.1.3.3
Summary: Prompt eval CLI to stress test agents and generate robust prompts.
Author-email: davismartens <hellochuff@gmail.com>
License: MIT
Project-URL: Homepage, https://github.com/davismartens/ev
Keywords: llm,prompt,prompt,prompt-eval,agent-evals,ai-agent-testing,ai-testing,ai,cli,testing,agents,evals,openai,anthropic,groq,google-gemini
Classifier: Programming Language :: Python :: 3
Classifier: License :: OSI Approved :: MIT License
Classifier: Operating System :: OS Independent
Classifier: Environment :: Console
Classifier: Topic :: Software Development :: Testing
Classifier: Topic :: Scientific/Engineering :: Artificial Intelligence
Requires-Python: >=3.12
License-File: LICENSE
Requires-Dist: python-decouple
Requires-Dist: pydantic-settings
Requires-Dist: pydantic
Requires-Dist: Jinja2
Requires-Dist: typer
Requires-Dist: rich
Requires-Dist: openai
Requires-Dist: groq
Dynamic: license-file
